ep_transition/__init__.py
ep_transition/energyPlus_path.py
ep_transition/gui.py
ep_transition/international.py
ep_transition/runner.py
ep_transition/transition_binary.py
ep_transition/transition_run_thread.py
ep_transition_tools-2.0.2.dist-info/LICENSE.txt
ep_transition_tools-2.0.2.dist-info/METADATA
ep_transition_tools-2.0.2.dist-info/WHEEL
ep_transition_tools-2.0.2.dist-info/entry_points.txt
ep_transition_tools-2.0.2.dist-info/top_level.txt
ep_transition_tools-2.0.2.dist-info/RECORD
