Metadata-Version: 2.1
Name: ep-transition-tools
Version: 2.0.2
Summary: A library and tkinter-based tool for transitioning EnergyPlus input files
Home-page: https://github.com/myoldmopar/idfversionupdater2
Author: Edwin Lee via NREL via United States Department of Energy
License: UNKNOWN
Platform: UNKNOWN
